malnet_task-0.1.0-py3.7-nspkg.pth
malnet/task/__init__.py
malnet/task/core.py
malnet_task-0.1.0.dist-info/LICENSE
malnet_task-0.1.0.dist-info/METADATA
malnet_task-0.1.0.dist-info/WHEEL
malnet_task-0.1.0.dist-info/namespace_packages.txt
malnet_task-0.1.0.dist-info/top_level.txt
malnet_task-0.1.0.dist-info/zip-safe
malnet_task-0.1.0.dist-info/RECORD
